AUTHORS.rst
CONTRIBUTING.rst
LICENSE
MANIFEST.in
README.md
setup.cfg
setup.py
docs/Makefile
docs/authors.rst
docs/conf.py
docs/contributing.rst
docs/history.rst
docs/index.rst
docs/installation.rst
docs/make.bat
docs/readme.rst
docs/usage.rst
gitleaves/__init__.py
gitleaves/cli.py
gitleaves/gitleaves.py
gitleaves/reports.py
gitleaves.egg-info/PKG-INFO
gitleaves.egg-info/SOURCES.txt
gitleaves.egg-info/dependency_links.txt
gitleaves.egg-info/entry_points.txt
gitleaves.egg-info/not-zip-safe
gitleaves.egg-info/requires.txt
gitleaves.egg-info/top_level.txt
gitleaves/templates/ghwiki/Home.md
gitleaves/templates/ghwiki/Monthwise.md
gitleaves/templates/ghwiki/Yearwise.md
gitleaves/templates/ghwiki/_Sidebar.md
tests/__init__.py
tests/test_gitleaves.py