Metadata-Version: 2.1
Name: gitleaves
Version: 0.6.4
Summary: Git Based Leaves management system
Home-page: https://github.com/scrollstack/gitleaves
Author: Shekhar Tiwatne
Author-email: pythonic@gmail.com
License: MIT license
Keywords: gitleaves
Platform: UNKNOWN
Classifier: Development Status :: 2 - Pre-Alpha
Classifier: Intended Audience :: Developers
Classifier: License :: OSI Approved :: MIT License
Classifier: Natural Language :: English
Classifier: Programming Language :: Python :: 3
Classifier: Programming Language :: Python :: 3.6
Classifier: Programming Language :: Python :: 3.7
Classifier: Programming Language :: Python :: 3.8
Requires-Python: >=3.6
License-File: LICENSE
License-File: AUTHORS.rst
